shipyard_shortcut/__init__.py
shipyard_shortcut/cli/add_comment.py
shipyard_shortcut/cli/create_ticket.py
shipyard_shortcut/cli/edit_ticket.py
shipyard_shortcut/error_handler.py
shipyard_shortcut/shortcut.py
shipyard_shortcut-0.1.3.dist-info/METADATA
shipyard_shortcut-0.1.3.dist-info/WHEEL
shipyard_shortcut-0.1.3.dist-info/RECORD
